README.txt
setup.cfg
setup.py
KalturaClient/Base.py
KalturaClient/Client.py
KalturaClient/__init__.py
KalturaClient/Plugins/AdCuePoint.py
KalturaClient/Plugins/AdminConsole.py
KalturaClient/Plugins/Annotation.py
KalturaClient/Plugins/Attachment.py
KalturaClient/Plugins/BulkUpload.py
KalturaClient/Plugins/BulkUploadCsv.py
KalturaClient/Plugins/BulkUploadFilter.py
KalturaClient/Plugins/BulkUploadXml.py
KalturaClient/Plugins/Caption.py
KalturaClient/Plugins/CaptionSearch.py
KalturaClient/Plugins/CodeCuePoint.py
KalturaClient/Plugins/ContentDistribution.py
KalturaClient/Plugins/Core.py
KalturaClient/Plugins/CuePoint.py
KalturaClient/Plugins/Document.py
KalturaClient/Plugins/DropFolder.py
KalturaClient/Plugins/DropFolderXmlBulkUpload.py
KalturaClient/Plugins/EmailNotification.py
KalturaClient/Plugins/EventCuePoint.py
KalturaClient/Plugins/EventNotification.py
KalturaClient/Plugins/ExternalMedia.py
KalturaClient/Plugins/FeedDropFolder.py
KalturaClient/Plugins/FileSync.py
KalturaClient/Plugins/HttpNotification.py
KalturaClient/Plugins/KalturaInternalTools.py
KalturaClient/Plugins/Kontiki.py
KalturaClient/Plugins/Like.py
KalturaClient/Plugins/Metadata.py
KalturaClient/Plugins/Quiz.py
KalturaClient/Plugins/ScheduledTask.py
KalturaClient/Plugins/ScheduledTaskContentDistribution.py
KalturaClient/Plugins/ScheduledTaskEventNotification.py
KalturaClient/Plugins/ScheduledTaskMetadata.py
KalturaClient/Plugins/ShortLink.py
KalturaClient/Plugins/SystemPartner.py
KalturaClient/Plugins/TagSearch.py
KalturaClient/Plugins/ThumbCuePoint.py
KalturaClient/Plugins/VarConsole.py
KalturaClient/Plugins/Velocix.py
KalturaClient/Plugins/VirusScan.py
KalturaClient/Plugins/__init__.py
python_kaltura.egg-info/PKG-INFO
python_kaltura.egg-info/SOURCES.txt
python_kaltura.egg-info/dependency_links.txt
python_kaltura.egg-info/pbr.json
python_kaltura.egg-info/requires.txt
python_kaltura.egg-info/top_level.txt