Metadata-Version: 1.1
Name: python-kaltura
Version: 1.0.0
Summary: A Python module for accessing the Kaltura API.
Home-page: https://github.com/ptchankue/KalturaGeneratedAPIClientsPython
Author: Patrick Tchankue
Author-email: ptchankue@gmail.com
License: AGPL
Download-URL: https://github.com/ptchankue/KalturaGeneratedAPIClientsPython/tarball/0.1
Keywords: kaltura,python,django,flask
Platform: UNKNOWN
